Guguji.py
setup.py
Guguji.egg-info/PKG-INFO
Guguji.egg-info/SOURCES.txt
Guguji.egg-info/dependency_links.txt
Guguji.egg-info/requires.txt
Guguji.egg-info/top_level.txt