Metadata-Version: 1.0
Name: Guguji
Version: 0.2
Summary: A python api for memobird guguji
Home-page: https://github.com/auzn/Guguji
Author: auzn
Author-email: auzn.cn@gmail.com
License: MIT
Keywords: memobird guguji
Platform: UNKNOWN
